{
  "algo":"hspa",
  "region":"Alabama",
  "time_slots":120,
  "arrival_rate":20.0,
  "mean_service_time":9.0,
  "seed":4,
  "trace_seed":8232878860584286532,
  "algo_seed":11781817971983258927,
  "trace_hash":"73ddec1fddd72840ca0047ebd936137f3e733fc5696629341fcf6cecb8673a33",
  "arrivals_per_slot":[
    14,
    21,
    19,
    18,
    22,
    21,
    21,
    16,
    15,
    27,
    22,
    21,
    23,
    17,
    20,
    22,
    24,
    17,
    15,
    24,
    29,
    24,
    15,
    22,
    22,
    13,
    21,
    17,
    23,
    14,
    29,
    22,
    25,
    22,
    22,
    24,
    29,
    29,
    22,
    24,
    23,
    18,
    16,
    11,
    23,
    17,
    30,
    19,
    19,
    25,
    18,
    29,
    17,
    20,
    26,
    17,
    22,
    15,
    17,
    25,
    20,
    19,
    14,
    18,
    19,
    19,
    20,
    18,
    21,
    24,
    26,
    25,
    24,
    18,
    22,
    15,
    16,
    17,
    17,
    19,
    32,
    19,
    25,
    24,
    18,
    16,
    15,
    21,
    19,
    25,
    12,
    21,
    40,
    19,
    17,
    20,
    17,
    16,
    17,
    16,
    20,
    25,
    9,
    19,
    21,
    14,
    13,
    22,
    17,
    24,
    29,
    16,
    19,
    20,
    35,
    14,
    14,
    22,
    18,
    16
  ],
  "diversity":false,
  "p_split":null,
  "split_reliability_mode":null,
  "mechanism":null,
  "fixed_sfc_len":4,
  "fixed_reliability":null,
  "max_backup_level":2,
  "explicit_split_replicas":false,
  "split_enforce_distinct":false,
  "strict_split_resource_ablation":false,
  "split_replica_resource_scale":1.0,
  "cap_base_min":500,
  "cap_base_max":700,
  "cap_scale":0.2,
  "total_arrivals":2441,
  "total_accepted":1250,
  "total_rejected":1191,
  "acceptance_ratio":0.512085211,
  "avg_cost_per_arrival":37.2802733601,
  "total_cost":91001.1472720081,
  "total_cost_resource":69327.147272008,
  "avg_cost_per_accepted":72.8009178176,
  "final_utilization":0.9654941292,
  "avg_utilization_over_time":0.9460734349,
  "avg_leftover_capacity_sum_over_time":9316.925,
  "final_leftover_capacity_sum":5961.6,
  "final_leftover_capacity_min":0.0,
  "final_leftover_capacity_max":175.0,
  "final_leftover_capacity_avg":43.5153284672,
  "avg_e2e_delay_accepted":0.0847217301,
  "p95_e2e_delay_accepted":0.1407285704,
  "avg_access_delay_accepted":0.0080635879,
  "avg_processing_delay_accepted":0.0660399671,
  "avg_network_delay_accepted":0.0106181751,
  "avg_split_proc_overhead_accepted":0.0,
  "avg_split_net_overhead_accepted":0.0,
  "total_transmitted_bits_accepted":2469656695.1654286385,
  "avg_transmitted_bits_per_accepted":1975725.3561323429,
  "total_split_transmitted_bits_accepted":0.0,
  "avg_split_transmitted_bits_per_accepted":0.0,
  "avg_split_overhead_ratio_accepted":0.0,
  "p95_split_overhead_ratio_accepted":0.0,
  "rga_accepted_total":2441,
  "rga_rejected_total":0,
  "rga_rejection_ratio":0.0,
  "mdca_rejected_total":1191,
  "mdca_capacity_rejected_total":1173,
  "mdca_reliability_rejected_total":0,
  "mdca_qos_rejected_total":18,
  "mdca_rejection_ratio":0.487914789,
  "capacity_rejection_ratio":0.480540762,
  "reliability_rejection_ratio":0.0,
  "qos_rejected_total":18,
  "qos_rejection_ratio":0.007374027
}