{
  "algo":"mdca",
  "region":"Alabama",
  "time_slots":120,
  "arrival_rate":12.0,
  "mean_service_time":9.0,
  "seed":3,
  "trace_seed":8849697010647911005,
  "algo_seed":1140299112174461975,
  "trace_hash":"f525e59b369e59b8a55fd65b95aac42a13d420159403165468d17b103fa88798",
  "arrivals_per_slot":[
    10,
    10,
    19,
    9,
    10,
    8,
    12,
    13,
    16,
    9,
    12,
    6,
    7,
    14,
    9,
    13,
    8,
    18,
    20,
    13,
    8,
    9,
    10,
    12,
    12,
    11,
    9,
    11,
    6,
    11,
    11,
    9,
    12,
    16,
    10,
    10,
    9,
    6,
    16,
    11,
    14,
    12,
    14,
    10,
    14,
    7,
    11,
    6,
    13,
    14,
    17,
    12,
    10,
    7,
    13,
    13,
    18,
    11,
    9,
    21,
    8,
    7,
    17,
    10,
    6,
    15,
    6,
    9,
    16,
    7,
    16,
    12,
    9,
    19,
    14,
    13,
    6,
    12,
    18,
    11,
    16,
    10,
    12,
    15,
    6,
    8,
    11,
    10,
    11,
    19,
    8,
    10,
    4,
    17,
    7,
    9,
    15,
    8,
    12,
    16,
    18,
    16,
    10,
    11,
    21,
    14,
    13,
    7,
    17,
    13,
    14,
    13,
    16,
    16,
    13,
    12,
    15,
    10,
    16,
    17
  ],
  "diversity":true,
  "p_split":0.3,
  "split_reliability_mode":"identical_active_pool",
  "mechanism":null,
  "fixed_sfc_len":null,
  "fixed_reliability":0.998,
  "max_backup_level":5,
  "explicit_split_replicas":true,
  "split_enforce_distinct":false,
  "strict_split_resource_ablation":false,
  "split_replica_resource_scale":1.0,
  "cap_base_min":500,
  "cap_base_max":700,
  "cap_scale":0.2,
  "total_arrivals":1428,
  "total_accepted":1335,
  "total_rejected":93,
  "acceptance_ratio":0.9348739496,
  "avg_cost_per_arrival":56.3147400329,
  "total_cost":80417.4487669269,
  "total_cost_resource":58799.4487669269,
  "avg_cost_per_accepted":60.2377893385,
  "final_utilization":0.9534999343,
  "avg_utilization_over_time":0.8541852155,
  "avg_leftover_capacity_sum_over_time":25515.9833333333,
  "final_leftover_capacity_sum":8137.0,
  "final_leftover_capacity_min":0.0,
  "final_leftover_capacity_max":797.0,
  "final_leftover_capacity_avg":59.3941605839,
  "avg_e2e_delay_accepted":0.0669030301,
  "p95_e2e_delay_accepted":0.1278431557,
  "avg_access_delay_accepted":0.0080009838,
  "avg_processing_delay_accepted":0.0437634157,
  "avg_network_delay_accepted":0.0118853476,
  "avg_split_proc_overhead_accepted":5.161939332e-19,
  "avg_split_net_overhead_accepted":0.0,
  "total_transmitted_bits_accepted":2266104513.339056015,
  "avg_transmitted_bits_per_accepted":1697456.5642989185,
  "total_split_transmitted_bits_accepted":501212726.1080383658,
  "avg_split_transmitted_bits_per_accepted":375440.2442756842,
  "avg_split_overhead_ratio_accepted":6.712799632e-18,
  "p95_split_overhead_ratio_accepted":4.124392342e-17,
  "rga_accepted_total":1428,
  "rga_rejected_total":0,
  "rga_rejection_ratio":0.0,
  "mdca_rejected_total":93,
  "mdca_capacity_rejected_total":75,
  "mdca_reliability_rejected_total":0,
  "mdca_qos_rejected_total":18,
  "mdca_rejection_ratio":0.0651260504,
  "capacity_rejection_ratio":0.0525210084,
  "reliability_rejection_ratio":0.0,
  "qos_rejected_total":18,
  "qos_rejection_ratio":0.012605042
}