{
  "algo":"mdca",
  "region":"Alabama",
  "time_slots":120,
  "arrival_rate":12.0,
  "mean_service_time":9.0,
  "seed":2,
  "trace_seed":2442432397383401356,
  "algo_seed":9454931305527635803,
  "trace_hash":"7e52d31fdb5bd15ae4c86921d484cd899b8682060d2a83514ca66c5a44c638bc",
  "arrivals_per_slot":[
    14,
    10,
    13,
    11,
    12,
    14,
    9,
    7,
    8,
    9,
    15,
    20,
    17,
    7,
    15,
    13,
    16,
    10,
    6,
    13,
    14,
    16,
    15,
    3,
    15,
    9,
    9,
    11,
    16,
    14,
    12,
    13,
    16,
    17,
    12,
    6,
    17,
    15,
    11,
    15,
    15,
    10,
    10,
    12,
    12,
    9,
    13,
    13,
    11,
    13,
    13,
    15,
    10,
    11,
    11,
    13,
    12,
    17,
    12,
    13,
    15,
    12,
    6,
    14,
    8,
    11,
    16,
    18,
    11,
    13,
    13,
    15,
    8,
    11,
    10,
    14,
    13,
    10,
    15,
    12,
    19,
    8,
    7,
    7,
    11,
    17,
    8,
    13,
    8,
    7,
    8,
    13,
    14,
    20,
    8,
    10,
    9,
    16,
    13,
    15,
    8,
    6,
    10,
    7,
    14,
    14,
    11,
    9,
    14,
    13,
    12,
    12,
    18,
    6,
    17,
    11,
    11,
    9,
    9,
    14
  ],
  "diversity":true,
  "p_split":0.3,
  "split_reliability_mode":"identical_active_pool",
  "mechanism":null,
  "fixed_sfc_len":null,
  "fixed_reliability":0.996,
  "max_backup_level":2,
  "explicit_split_replicas":true,
  "split_enforce_distinct":false,
  "strict_split_resource_ablation":false,
  "split_replica_resource_scale":1.0,
  "cap_base_min":500,
  "cap_base_max":700,
  "cap_scale":0.2,
  "total_arrivals":1441,
  "total_accepted":1393,
  "total_rejected":48,
  "acceptance_ratio":0.9666897988,
  "avg_cost_per_arrival":57.4143884006,
  "total_cost":82734.1336852917,
  "total_cost_resource":55891.1336852917,
  "avg_cost_per_accepted":59.3927736434,
  "final_utilization":0.8751800477,
  "avg_utilization_over_time":0.811105843,
  "avg_leftover_capacity_sum_over_time":32549.3722222222,
  "final_leftover_capacity_sum":21508.4,
  "final_leftover_capacity_min":0.3333333333,
  "final_leftover_capacity_max":1932.8,
  "final_leftover_capacity_avg":156.995620438,
  "avg_e2e_delay_accepted":0.0698531441,
  "p95_e2e_delay_accepted":0.1342059763,
  "avg_access_delay_accepted":0.0080182302,
  "avg_processing_delay_accepted":0.0416755788,
  "avg_network_delay_accepted":0.014770902,
  "avg_split_proc_overhead_accepted":6.84923124e-19,
  "avg_split_net_overhead_accepted":0.0,
  "total_transmitted_bits_accepted":2774940622.052734375,
  "avg_transmitted_bits_per_accepted":1992060.7480637003,
  "total_split_transmitted_bits_accepted":921149813.9698431492,
  "avg_split_transmitted_bits_per_accepted":661270.5053624143,
  "avg_split_overhead_ratio_accepted":8.490645918e-18,
  "p95_split_overhead_ratio_accepted":5.696826133e-17,
  "rga_accepted_total":1441,
  "rga_rejected_total":0,
  "rga_rejection_ratio":0.0,
  "mdca_rejected_total":48,
  "mdca_capacity_rejected_total":30,
  "mdca_reliability_rejected_total":2,
  "mdca_qos_rejected_total":16,
  "mdca_rejection_ratio":0.0333102012,
  "capacity_rejection_ratio":0.0208188758,
  "reliability_rejection_ratio":0.0013879251,
  "qos_rejected_total":16,
  "qos_rejection_ratio":0.0111034004
}