{
  "algo":"mdca",
  "region":"Alabama",
  "time_slots":120,
  "arrival_rate":40.0,
  "mean_service_time":9.0,
  "seed":2,
  "trace_seed":4086735128279936581,
  "algo_seed":1988428424119012433,
  "trace_hash":"b037f8f05b2a055d9074b207f78a70c932d96437b0f149b41720d47d8426b8aa",
  "arrivals_per_slot":[
    41,
    50,
    37,
    30,
    45,
    39,
    47,
    37,
    45,
    44,
    45,
    49,
    33,
    44,
    43,
    36,
    36,
    53,
    45,
    37,
    47,
    54,
    42,
    39,
    36,
    28,
    41,
    41,
    31,
    52,
    50,
    41,
    33,
    52,
    50,
    41,
    52,
    50,
    41,
    43,
    50,
    41,
    55,
    46,
    42,
    30,
    51,
    37,
    41,
    35,
    42,
    37,
    52,
    32,
    34,
    43,
    34,
    45,
    39,
    34,
    56,
    41,
    40,
    33,
    41,
    47,
    37,
    38,
    43,
    40,
    50,
    46,
    41,
    41,
    39,
    30,
    46,
    39,
    34,
    46,
    32,
    47,
    36,
    42,
    48,
    30,
    41,
    27,
    50,
    42,
    48,
    47,
    35,
    35,
    34,
    53,
    32,
    40,
    48,
    41,
    38,
    37,
    45,
    53,
    42,
    38,
    32,
    29,
    44,
    41,
    43,
    35,
    36,
    33,
    45,
    32,
    41,
    48,
    43,
    30
  ],
  "diversity":true,
  "p_split":0.3,
  "split_reliability_mode":"identical_active_pool",
  "mechanism":null,
  "fixed_sfc_len":null,
  "fixed_reliability":null,
  "max_backup_level":2,
  "explicit_split_replicas":true,
  "split_enforce_distinct":false,
  "strict_split_resource_ablation":false,
  "split_replica_resource_scale":1.0,
  "cap_base_min":500,
  "cap_base_max":700,
  "cap_scale":0.2,
  "total_arrivals":4941,
  "total_accepted":3248,
  "total_rejected":1693,
  "acceptance_ratio":0.6573568104,
  "avg_cost_per_arrival":20.4015483227,
  "total_cost":100804.0502623937,
  "total_cost_resource":72562.0502623937,
  "avg_cost_per_accepted":31.0357297606,
  "final_utilization":0.964366795,
  "avg_utilization_over_time":0.9527628195,
  "avg_leftover_capacity_sum_over_time":8103.6138888889,
  "final_leftover_capacity_sum":6112.9333333333,
  "final_leftover_capacity_min":0.0,
  "final_leftover_capacity_max":709.4,
  "final_leftover_capacity_avg":44.6199513382,
  "avg_e2e_delay_accepted":0.0627528635,
  "p95_e2e_delay_accepted":0.128262116,
  "avg_access_delay_accepted":0.0080166562,
  "avg_processing_delay_accepted":0.0416064791,
  "avg_network_delay_accepted":0.0099783694,
  "avg_split_proc_overhead_accepted":5.573226438e-19,
  "avg_split_net_overhead_accepted":0.0,
  "total_transmitted_bits_accepted":4576830616.7013263702,
  "avg_transmitted_bits_per_accepted":1409122.7268169108,
  "total_split_transmitted_bits_accepted":1121859774.8049566746,
  "avg_split_transmitted_bits_per_accepted":345400.1769719694,
  "avg_split_overhead_ratio_accepted":7.066543812e-18,
  "p95_split_overhead_ratio_accepted":4.945298708e-17,
  "rga_accepted_total":4941,
  "rga_rejected_total":0,
  "rga_rejection_ratio":0.0,
  "mdca_rejected_total":1693,
  "mdca_capacity_rejected_total":1649,
  "mdca_reliability_rejected_total":3,
  "mdca_qos_rejected_total":41,
  "mdca_rejection_ratio":0.3426431896,
  "capacity_rejection_ratio":0.3337381097,
  "reliability_rejection_ratio":0.0006071645,
  "qos_rejected_total":41,
  "qos_rejection_ratio":0.0082979154
}