{
  "algo":"hspa",
  "region":"Arizona",
  "time_slots":120,
  "arrival_rate":20.0,
  "mean_service_time":9.0,
  "seed":5,
  "trace_seed":768280190002632348,
  "algo_seed":17931641280568136439,
  "trace_hash":"0a25e4aff5babb2466fa239bc7a8b804ccc863ada88559b4baa8f87da0abb4b1",
  "arrivals_per_slot":[
    19,
    21,
    22,
    24,
    25,
    15,
    24,
    17,
    14,
    15,
    17,
    19,
    27,
    27,
    14,
    21,
    25,
    21,
    23,
    23,
    19,
    27,
    21,
    23,
    22,
    14,
    19,
    18,
    28,
    23,
    14,
    17,
    22,
    17,
    15,
    20,
    22,
    12,
    22,
    28,
    14,
    24,
    25,
    15,
    16,
    21,
    15,
    25,
    20,
    23,
    17,
    29,
    18,
    27,
    21,
    24,
    17,
    13,
    22,
    19,
    25,
    14,
    20,
    20,
    19,
    16,
    19,
    20,
    20,
    17,
    22,
    17,
    17,
    21,
    19,
    16,
    26,
    15,
    19,
    12,
    16,
    14,
    23,
    13,
    20,
    17,
    17,
    24,
    23,
    17,
    13,
    17,
    18,
    19,
    16,
    28,
    15,
    22,
    15,
    24,
    26,
    11,
    21,
    25,
    23,
    19,
    20,
    16,
    17,
    24,
    21,
    22,
    20,
    16,
    20,
    12,
    13,
    19,
    14,
    14
  ],
  "diversity":false,
  "p_split":null,
  "split_reliability_mode":null,
  "mechanism":null,
  "fixed_sfc_len":4,
  "fixed_reliability":null,
  "max_backup_level":2,
  "explicit_split_replicas":false,
  "split_enforce_distinct":false,
  "strict_split_resource_ablation":false,
  "split_replica_resource_scale":1.0,
  "cap_base_min":500,
  "cap_base_max":700,
  "cap_scale":0.2,
  "total_arrivals":2339,
  "total_accepted":2305,
  "total_rejected":34,
  "acceptance_ratio":0.9854638735,
  "avg_cost_per_arrival":65.7704531262,
  "total_cost":153837.0898622454,
  "total_cost_resource":113878.0898622454,
  "avg_cost_per_accepted":66.7406029771,
  "final_utilization":0.7318674272,
  "avg_utilization_over_time":0.7889581914,
  "avg_leftover_capacity_sum_over_time":78989.7833333333,
  "final_leftover_capacity_sum":100358.0,
  "final_leftover_capacity_min":0.0,
  "final_leftover_capacity_max":2162.2,
  "final_leftover_capacity_avg":319.6114649682,
  "avg_e2e_delay_accepted":0.0840440717,
  "p95_e2e_delay_accepted":0.1360022823,
  "avg_access_delay_accepted":0.0080332772,
  "avg_processing_delay_accepted":0.0633703462,
  "avg_network_delay_accepted":0.0126404483,
  "avg_split_proc_overhead_accepted":0.0,
  "avg_split_net_overhead_accepted":0.0,
  "total_transmitted_bits_accepted":4635069857.8658027649,
  "avg_transmitted_bits_per_accepted":2010876.2940849469,
  "total_split_transmitted_bits_accepted":0.0,
  "avg_split_transmitted_bits_per_accepted":0.0,
  "avg_split_overhead_ratio_accepted":0.0,
  "p95_split_overhead_ratio_accepted":0.0,
  "rga_accepted_total":2339,
  "rga_rejected_total":0,
  "rga_rejection_ratio":0.0,
  "mdca_rejected_total":34,
  "mdca_capacity_rejected_total":0,
  "mdca_reliability_rejected_total":0,
  "mdca_qos_rejected_total":34,
  "mdca_rejection_ratio":0.0145361265,
  "capacity_rejection_ratio":0.0,
  "reliability_rejection_ratio":0.0,
  "qos_rejected_total":34,
  "qos_rejection_ratio":0.0145361265
}