{
  "algo":"hspa",
  "region":"Arizona",
  "time_slots":120,
  "arrival_rate":12.0,
  "mean_service_time":9.0,
  "seed":5,
  "trace_seed":11454857388609130654,
  "algo_seed":17931641280568136439,
  "trace_hash":"ef0d3052f2f87837fe9bfc0d4dc3077813e31953f7484c62deefbd25715f517c",
  "arrivals_per_slot":[
    13,
    16,
    12,
    13,
    10,
    11,
    9,
    12,
    8,
    8,
    15,
    8,
    10,
    11,
    11,
    11,
    13,
    9,
    8,
    14,
    7,
    11,
    8,
    13,
    11,
    14,
    7,
    16,
    12,
    7,
    8,
    12,
    13,
    10,
    9,
    13,
    15,
    10,
    13,
    8,
    15,
    13,
    8,
    15,
    10,
    11,
    18,
    10,
    14,
    6,
    9,
    13,
    18,
    14,
    20,
    14,
    11,
    11,
    11,
    9,
    9,
    13,
    16,
    18,
    7,
    12,
    11,
    8,
    17,
    7,
    14,
    8,
    13,
    9,
    16,
    13,
    10,
    14,
    19,
    16,
    14,
    9,
    7,
    12,
    12,
    9,
    12,
    7,
    14,
    11,
    10,
    18,
    17,
    18,
    16,
    10,
    9,
    15,
    11,
    9,
    12,
    13,
    15,
    12,
    10,
    13,
    8,
    12,
    13,
    13,
    9,
    10,
    10,
    13,
    11,
    9,
    8,
    10,
    8,
    10
  ],
  "diversity":false,
  "p_split":null,
  "split_reliability_mode":null,
  "mechanism":null,
  "fixed_sfc_len":null,
  "fixed_reliability":0.999,
  "max_backup_level":2,
  "explicit_split_replicas":false,
  "split_enforce_distinct":false,
  "strict_split_resource_ablation":false,
  "split_replica_resource_scale":1.0,
  "cap_base_min":500,
  "cap_base_max":700,
  "cap_scale":0.2,
  "total_arrivals":1398,
  "total_accepted":889,
  "total_rejected":509,
  "acceptance_ratio":0.6359084406,
  "avg_cost_per_arrival":26.1744230675,
  "total_cost":36591.8434484164,
  "total_cost_resource":23321.8434484164,
  "avg_cost_per_accepted":41.1606787946,
  "final_utilization":0.3238727513,
  "avg_utilization_over_time":0.2667371427,
  "avg_leftover_capacity_sum_over_time":276168.3499999999,
  "final_leftover_capacity_sum":254649.4,
  "final_leftover_capacity_min":1.0,
  "final_leftover_capacity_max":2306.6,
  "final_leftover_capacity_avg":810.9853503185,
  "avg_e2e_delay_accepted":0.0555094896,
  "p95_e2e_delay_accepted":0.1158192044,
  "avg_access_delay_accepted":0.0080223948,
  "avg_processing_delay_accepted":0.0409580318,
  "avg_network_delay_accepted":0.006529063,
  "avg_split_proc_overhead_accepted":0.0,
  "avg_split_net_overhead_accepted":0.0,
  "total_transmitted_bits_accepted":907102700.7527189255,
  "avg_transmitted_bits_per_accepted":1020362.9929726872,
  "total_split_transmitted_bits_accepted":0.0,
  "avg_split_transmitted_bits_per_accepted":0.0,
  "avg_split_overhead_ratio_accepted":0.0,
  "p95_split_overhead_ratio_accepted":0.0,
  "rga_accepted_total":893,
  "rga_rejected_total":505,
  "rga_rejection_ratio":0.361230329,
  "mdca_rejected_total":4,
  "mdca_capacity_rejected_total":0,
  "mdca_reliability_rejected_total":0,
  "mdca_qos_rejected_total":4,
  "mdca_rejection_ratio":0.0028612303,
  "capacity_rejection_ratio":0.0,
  "reliability_rejection_ratio":0.0,
  "qos_rejected_total":4,
  "qos_rejection_ratio":0.0028612303
}